odoo/addons/pos_receipt_hide_info/README.rst
odoo/addons/pos_receipt_hide_info/__init__.py
odoo/addons/pos_receipt_hide_info/__manifest__.py
odoo/addons/pos_receipt_hide_info/i18n/it.po
odoo/addons/pos_receipt_hide_info/i18n/pos_receipt_hide_info.pot
odoo/addons/pos_receipt_hide_info/models/__init__.py
odoo/addons/pos_receipt_hide_info/models/pos_config.py
odoo/addons/pos_receipt_hide_info/models/res_config_settings.py
odoo/addons/pos_receipt_hide_info/readme/CONTRIBUTORS.rst
odoo/addons/pos_receipt_hide_info/readme/CREDITS.rst
odoo/addons/pos_receipt_hide_info/readme/DESCRIPTION.rst
odoo/addons/pos_receipt_hide_info/static/description/icon.png
odoo/addons/pos_receipt_hide_info/static/description/index.html
odoo/addons/pos_receipt_hide_info/static/src/js/order_receipt.js
odoo/addons/pos_receipt_hide_info/static/src/xml/order_receipt.xml
odoo/addons/pos_receipt_hide_info/views/res_config_settings.xml
odoo_addon_pos_receipt_hide_info-16.0.1.0.0.4.dist-info/METADATA
odoo_addon_pos_receipt_hide_info-16.0.1.0.0.4.dist-info/WHEEL
odoo_addon_pos_receipt_hide_info-16.0.1.0.0.4.dist-info/top_level.txt
odoo_addon_pos_receipt_hide_info-16.0.1.0.0.4.dist-info/RECORD
